gwatn/__init__.py
gwatn/__main__.py
gwatn/api_types.py
gwatn/atn_actor_base.py
gwatn/atn_utils.py
gwatn/config.py
gwatn/conversion_factors.py
gwatn/data_classes/.DS_Store
gwatn/data_classes/__init__.py
gwatn/data_classes/d_edge.py
gwatn/data_classes/d_graph.py
gwatn/data_classes/d_node.py
gwatn/data_classes/hack_price_method.py
gwatn/data_classes/hack_weather_location.py
gwatn/data_classes/hack_weather_source.py
gwatn/demo_methods.py
gwatn/dev_utils/__init__.py
gwatn/dev_utils/dev_discoverer.py
gwatn/dev_utils/dev_ta_owner.py
gwatn/dev_utils/dev_validator.py
gwatn/dev_utils/make_plants.py
gwatn/dev_utils/price/actual_data/__init__.py
gwatn/dev_utils/price/actual_data/init_actual_prices_db.py
gwatn/dev_utils/price/actual_data/update_actual_price_db.py
gwatn/dev_utils/price/basic_eprt_handler.py
gwatn/dev_utils/price/distp_sync_100_handler.py
gwatn/dev_utils/price/eprt_forecast_sync_100_handler.py
gwatn/dev_utils/price/eprt_sync_100_handler.py
gwatn/dev_utils/price/forecast_data/__init__.py
gwatn/dev_utils/price/forecast_data/caiso/__init__.py
gwatn/dev_utils/price/forecast_data/ercot/__init__.py
gwatn/dev_utils/price/forecast_data/gw/__init__.py
gwatn/dev_utils/price/forecast_data/init_ps_db.py
gwatn/dev_utils/price/forecast_data/isone/__init__.py
gwatn/dev_utils/price/forecast_data/isone/distp__w.isone.stetson__2022__168__gw.me.versant.a1.res.ets__5311504b.csv
gwatn/dev_utils/price/forecast_data/miso/__init__.py
gwatn/dev_utils/price/forecast_data/update_forecast_price_db.py
gwatn/dev_utils/price/input_handler.py
gwatn/dev_utils/price/regp_sync_100_handler.py
gwatn/dispatch_contract.py
gwatn/dispatch_contract_artifacts/application.json
gwatn/dispatch_contract_artifacts/approval.teal
gwatn/dispatch_contract_artifacts/clear.teal
gwatn/dispatch_contract_artifacts/contract.json
gwatn/enums/__init__.py
gwatn/enums/distribution_tariff.py
gwatn/enums/energy_supply_type.py
gwatn/enums/hack_price_method.py
gwatn/enums/hack_recognized_p_node_alias.py
gridworks_atn-0.4.0.dist-info/LICENSE
gridworks_atn-0.4.0.dist-info/METADATA
gridworks_atn-0.4.0.dist-info/WHEEL
gridworks_atn-0.4.0.dist-info/entry_points.txt
gridworks_atn-0.4.0.dist-info/RECORD
