Metadata-Version: 2.1
Name: gridworks-atn
Version: 0.4.0
Summary: Gridworks Atn Spaceheat
Home-page: https://github.com/thegridelectric/gridworks-atn
License: None
Author: GridWorks
Author-email: gridworks@gridworks-consulting.com
Requires-Python: >=3.10,<4.0
Classifier: Development Status :: 2 - Pre-Alpha
Classifier: License :: Other/Proprietary License
Classifier: Programming Language :: Python :: 3
Classifier: Programming Language :: Python :: 3.10
Classifier: Programming Language :: Python :: 3.11
Requires-Dist: gridworks-proactor (>=0.2.2,<0.3.0)
Requires-Dist: gridworks-ps (>=0.0.1,<0.0.2)
Requires-Dist: numpy (>=1.23.4,<2.0.0)
Requires-Dist: paho-mqtt (>=1.6.1,<2.0.0)
Project-URL: Changelog, https://github.com/thegridelectric/gridworks-atn/releases
Project-URL: Documentation, https://gridworks-atn.readthedocs.io
Project-URL: Repository, https://github.com/thegridelectric/gridworks-atn
